kubeagi/llm_api_service/__init__.py
kubeagi/llm_api_service/base_qa_provider.py
kubeagi/llm_api_service/qa_provider_open_ai.py
kubeagi/llm_api_service/qa_provider_zhi_pu_ai_online.py
kubeagi/llm_prompt_template/__init__.py
kubeagi/llm_prompt_template/llm_prompt.py
kubeagi-0.0.4.dist-info/LICENSE
kubeagi-0.0.4.dist-info/METADATA
kubeagi-0.0.4.dist-info/WHEEL
kubeagi-0.0.4.dist-info/top_level.txt
kubeagi-0.0.4.dist-info/RECORD
